cjh_project_builder/__init__.py
cjh_project_builder/cli.py
cjh_project_builder-0.1.2.dist-info/entry_points.txt
cjh_project_builder-0.1.2.dist-info/METADATA
cjh_project_builder-0.1.2.dist-info/WHEEL
cjh_project_builder-0.1.2.dist-info/RECORD
