Metadata-Version: 2.1
Name: cjh-project-builder
Version: 0.1.2
Summary: A CLI tool for generating FastAPI project structure
Author: jhcho
Author-email: cho418651@ssrinc.co.kr
Requires-Python: >=3.11,<4.0
Classifier: Programming Language :: Python :: 3
Classifier: Programming Language :: Python :: 3.11
Classifier: Programming Language :: Python :: 3.12
Requires-Dist: click (>=8.1.7,<9.0.0)
